[
    {
        "inputs": [
            {
                "internalType": "address",
                "name": "_btbToken",
                "type": "address"
            },
            {
                "internalType": "address",
                "name": "_vrfCoordinator",
                "type": "address"
            }
        ],
        "stateMutability": "nonpayable",
        "type": "constructor"
    },
    {
        "inputs": [],
        "name": "AlreadyCheckpointed",
        "type": "error"
    },
    {
        "inputs": [],
        "name": "InsufficientPayment",
        "type": "error"
    },
    {
        "inputs": [],
        "name": "InvalidDeployment",
        "type": "error"
    },
    {
        "inputs": [],
        "name": "InvalidPartner",
        "type": "error"
    },
    {
        "inputs": [],
        "name": "InvalidSquare",
        "type": "error"
    },
    {
        "inputs": [],
        "name": "MiningEnded",
        "type": "error"
    },
    {
        "inputs": [],
        "name": "MiningNotStarted",
        "type": "error"
    },
    {
        "inputs": [],
        "name": "NoRewardsToClaim",
        "type": "error"
    },
    {
        "inputs": [
            {
                "internalType": "address",
                "name": "owner",
                "type": "address"
            }
        ],
        "name": "OwnableInvalidOwner",
        "type": "error"
    },
    {
        "inputs": [
            {
                "internalType": "address",
                "name": "account",
                "type": "address"
            }
        ],
        "name": "OwnableUnauthorizedAccount",
        "type": "error"
    },
    {
        "inputs": [],
        "name": "PartnerAlreadyWhitelisted",
        "type": "error"
    },
    {
        "inputs": [],
        "name": "PartnerNotWhitelisted",
        "type": "error"
    },
    {
        "inputs": [],
        "name": "ReentrancyGuardReentrantCall",
        "type": "error"
    },
    {
        "inputs": [],
        "name": "RoundAlreadyFinalized",
        "type": "error"
    },
    {
        "inputs": [],
        "name": "RoundNotActive",
        "type": "error"
    },
    {
        "inputs": [],
        "name": "RoundNotFinalized",
        "type": "error"
    },
    {
        "inputs": [],
        "name": "RoundNotReadyForVRF",
        "type": "error"
    },
    {
        "inputs": [
            {
                "internalType": "address",
                "name": "token",
                "type": "address"
            }
        ],
        "name": "SafeERC20FailedOperation",
        "type": "error"
    },
    {
        "inputs": [],
        "name": "TransferFailed",
        "type": "error"
    },
    {
        "inputs": [],
        "name": "Unauthorized",
        "type": "error"
    },
    {
        "inputs": [],
        "name": "VRFRequestPending",
        "type": "error"
    },
    {
        "anonymous": false,
        "inputs": [
            {
                "indexed": false,
                "internalType": "uint256",
                "name": "amount",
                "type": "uint256"
            }
        ],
        "name": "AdminFeesSentToBondingCurve",
        "type": "event"
    },
    {
        "anonymous": false,
        "inputs": [
            {
                "indexed": true,
                "internalType": "address",
                "name": "miner",
                "type": "address"
            },
            {
                "indexed": false,
                "internalType": "uint256",
                "name": "refinedAmount",
                "type": "uint256"
            }
        ],
        "name": "BTBRefined",
        "type": "event"
    },
    {
        "anonymous": false,
        "inputs": [
            {
                "indexed": true,
                "internalType": "address",
                "name": "oldBondingCurve",
                "type": "address"
            },
            {
                "indexed": true,
                "internalType": "address",
                "name": "newBondingCurve",
                "type": "address"
            }
        ],
        "name": "BondingCurveAddressSet",
        "type": "event"
    },
    {
        "anonymous": false,
        "inputs": [
            {
                "indexed": true,
                "internalType": "uint256",
                "name": "roundId",
                "type": "uint256"
            },
            {
                "indexed": true,
                "internalType": "address",
                "name": "miner",
                "type": "address"
            },
            {
                "indexed": false,
                "internalType": "uint256",
                "name": "ethReward",
                "type": "uint256"
            },
            {
                "indexed": false,
                "internalType": "uint256",
                "name": "btbReward",
                "type": "uint256"
            },
            {
                "indexed": false,
                "internalType": "bool",
                "name": "isWinner",
                "type": "bool"
            }
        ],
        "name": "Checkpointed",
        "type": "event"
    },
    {
        "anonymous": false,
        "inputs": [
            {
                "indexed": true,
                "internalType": "uint256",
                "name": "roundId",
                "type": "uint256"
            },
            {
                "indexed": true,
                "internalType": "address",
                "name": "miner",
                "type": "address"
            },
            {
                "indexed": false,
                "internalType": "uint8[]",
                "name": "squares",
                "type": "uint8[]"
            },
            {
                "indexed": false,
                "internalType": "uint256",
                "name": "amountPerSquare",
                "type": "uint256"
            },
            {
                "indexed": false,
                "internalType": "uint256",
                "name": "totalAmount",
                "type": "uint256"
            }
        ],
        "name": "Deployed",
        "type": "event"
    },
    {
        "anonymous": false,
        "inputs": [
            {
                "indexed": true,
                "internalType": "uint256",
                "name": "roundId",
                "type": "uint256"
            },
            {
                "indexed": true,
                "internalType": "uint8",
                "name": "tier",
                "type": "uint8"
            },
            {
                "indexed": false,
                "internalType": "string",
                "name": "tierName",
                "type": "string"
            },
            {
                "indexed": false,
                "internalType": "uint256",
                "name": "amount",
                "type": "uint256"
            }
        ],
        "name": "MotherlodeHit",
        "type": "event"
    },
    {
        "anonymous": false,
        "inputs": [
            {
                "indexed": true,
                "internalType": "uint256",
                "name": "roundId",
                "type": "uint256"
            }
        ],
        "name": "MotherlodePotsIncreased",
        "type": "event"
    },
    {
        "anonymous": false,
        "inputs": [
            {
                "indexed": true,
                "internalType": "address",
                "name": "previousOwner",
                "type": "address"
            },
            {
                "indexed": true,
                "internalType": "address",
                "name": "newOwner",
                "type": "address"
            }
        ],
        "name": "OwnershipTransferred",
        "type": "event"
    },
    {
        "anonymous": false,
        "inputs": [
            {
                "indexed": true,
                "internalType": "address",
                "name": "partner",
                "type": "address"
            },
            {
                "indexed": true,
                "internalType": "address",
                "name": "recipient",
                "type": "address"
            },
            {
                "indexed": false,
                "internalType": "uint256",
                "name": "amount",
                "type": "uint256"
            }
        ],
        "name": "PartnerFeesWithdrawn",
        "type": "event"
    },
    {
        "anonymous": false,
        "inputs": [
            {
                "indexed": true,
                "internalType": "address",
                "name": "partner",
                "type": "address"
            }
        ],
        "name": "PartnerRemoved",
        "type": "event"
    },
    {
        "anonymous": false,
        "inputs": [
            {
                "indexed": true,
                "internalType": "address",
                "name": "partner",
                "type": "address"
            },
            {
                "indexed": false,
                "internalType": "string",
                "name": "name",
                "type": "string"
            }
        ],
        "name": "PartnerWhitelisted",
        "type": "event"
    },
    {
        "anonymous": false,
        "inputs": [
            {
                "indexed": true,
                "internalType": "uint256",
                "name": "roundId",
                "type": "uint256"
            },
            {
                "indexed": true,
                "internalType": "uint256",
                "name": "requestId",
                "type": "uint256"
            },
            {
                "indexed": false,
                "internalType": "uint256",
                "name": "randomness",
                "type": "uint256"
            }
        ],
        "name": "RandomnessReceived",
        "type": "event"
    },
    {
        "anonymous": false,
        "inputs": [
            {
                "indexed": true,
                "internalType": "address",
                "name": "user",
                "type": "address"
            },
            {
                "indexed": true,
                "internalType": "address",
                "name": "partner",
                "type": "address"
            },
            {
                "indexed": false,
                "internalType": "uint256",
                "name": "partnerCommission",
                "type": "uint256"
            },
            {
                "indexed": false,
                "internalType": "uint256",
                "name": "userCashback",
                "type": "uint256"
            }
        ],
        "name": "ReferralApplied",
        "type": "event"
    },
    {
        "anonymous": false,
        "inputs": [
            {
                "indexed": true,
                "internalType": "address",
                "name": "miner",
                "type": "address"
            },
            {
                "indexed": false,
                "internalType": "uint256",
                "name": "ethAmount",
                "type": "uint256"
            },
            {
                "indexed": false,
                "internalType": "uint256",
                "name": "btbAmount",
                "type": "uint256"
            },
            {
                "indexed": false,
                "internalType": "uint256",
                "name": "refinedBTB",
                "type": "uint256"
            },
            {
                "indexed": false,
                "internalType": "uint256",
                "name": "claimFee",
                "type": "uint256"
            }
        ],
        "name": "RewardsClaimed",
        "type": "event"
    },
    {
        "anonymous": false,
        "inputs": [
            {
                "indexed": true,
                "internalType": "uint256",
                "name": "roundId",
                "type": "uint256"
            }
        ],
        "name": "RoundDataPruned",
        "type": "event"
    },
    {
        "anonymous": false,
        "inputs": [
            {
                "indexed": true,
                "internalType": "uint256",
                "name": "roundId",
                "type": "uint256"
            },
            {
                "indexed": false,
                "internalType": "uint8",
                "name": "winningSquare",
                "type": "uint8"
            },
            {
                "indexed": false,
                "internalType": "uint256",
                "name": "totalWinnings",
                "type": "uint256"
            },
            {
                "indexed": false,
                "internalType": "uint256",
                "name": "btbReward",
                "type": "uint256"
            },
            {
                "indexed": false,
                "internalType": "uint256",
                "name": "totalMotherlodeReward",
                "type": "uint256"
            },
            {
                "indexed": false,
                "internalType": "uint16",
                "name": "motherlodeTiersHit",
                "type": "uint16"
            }
        ],
        "name": "RoundFinalized",
        "type": "event"
    },
    {
        "anonymous": false,
        "inputs": [
            {
                "indexed": true,
                "internalType": "uint256",
                "name": "roundId",
                "type": "uint256"
            },
            {
                "indexed": false,
                "internalType": "uint256",
                "name": "startTime",
                "type": "uint256"
            },
            {
                "indexed": false,
                "internalType": "uint256",
                "name": "endTime",
                "type": "uint256"
            }
        ],
        "name": "RoundStarted",
        "type": "event"
    },
    {
        "anonymous": false,
        "inputs": [
            {
                "indexed": true,
                "internalType": "address",
                "name": "oldTreasury",
                "type": "address"
            },
            {
                "indexed": true,
                "internalType": "address",
                "name": "newTreasury",
                "type": "address"
            }
        ],
        "name": "TreasuryAddressSet",
        "type": "event"
    },
    {
        "anonymous": false,
        "inputs": [
            {
                "indexed": false,
                "internalType": "uint256",
                "name": "totalWithdrawn",
                "type": "uint256"
            },
            {
                "indexed": false,
                "internalType": "uint256",
                "name": "toMotherlode",
                "type": "uint256"
            },
            {
                "indexed": false,
                "internalType": "uint256",
                "name": "toRewards",
                "type": "uint256"
            }
        ],
        "name": "TreasuryWithdrawal",
        "type": "event"
    },
    {
        "anonymous": false,
        "inputs": [
            {
                "indexed": true,
                "internalType": "uint256",
                "name": "roundId",
                "type": "uint256"
            },
            {
                "indexed": true,
                "internalType": "uint256",
                "name": "requestId",
                "type": "uint256"
            }
        ],
        "name": "VRFRequested",
        "type": "event"
    },
    {
        "inputs": [],
        "name": "ADMIN_FEE_BPS",
        "outputs": [
            {
                "internalType": "uint256",
                "name": "",
                "type": "uint256"
            }
        ],
        "stateMutability": "view",
        "type": "function"
    },
    {
        "inputs": [],
        "name": "BPS_DENOMINATOR",
        "outputs": [
            {
                "internalType": "uint256",
                "name": "",
                "type": "uint256"
            }
        ],
        "stateMutability": "view",
        "type": "function"
    },
    {
        "inputs": [],
        "name": "BRONZE_NUGGET_PROBABILITY",
        "outputs": [
            {
                "internalType": "uint256",
                "name": "",
                "type": "uint256"
            }
        ],
        "stateMutability": "view",
        "type": "function"
    },
    {
        "inputs": [],
        "name": "BTB_PER_MOTHERLODE_TIER_JACKPOT",
        "outputs": [
            {
                "internalType": "uint256",
                "name": "",
                "type": "uint256"
            }
        ],
        "stateMutability": "view",
        "type": "function"
    },
    {
        "inputs": [],
        "name": "BTB_PER_MOTHERLODE_TIER_NORMAL",
        "outputs": [
            {
                "internalType": "uint256",
                "name": "",
                "type": "uint256"
            }
        ],
        "stateMutability": "view",
        "type": "function"
    },
    {
        "inputs": [],
        "name": "BTB_PER_ROUND_JACKPOT",
        "outputs": [
            {
                "internalType": "uint256",
                "name": "",
                "type": "uint256"
            }
        ],
        "stateMutability": "view",
        "type": "function"
    },
    {
        "inputs": [],
        "name": "BTB_PER_ROUND_NORMAL",
        "outputs": [
            {
                "internalType": "uint256",
                "name": "",
                "type": "uint256"
            }
        ],
        "stateMutability": "view",
        "type": "function"
    },
    {
        "inputs": [],
        "name": "CLAIM_FEE_BPS",
        "outputs": [
            {
                "internalType": "uint256",
                "name": "",
                "type": "uint256"
            }
        ],
        "stateMutability": "view",
        "type": "function"
    },
    {
        "inputs": [],
        "name": "CRYSTAL_CACHE_PROBABILITY",
        "outputs": [
            {
                "internalType": "uint256",
                "name": "",
                "type": "uint256"
            }
        ],
        "stateMutability": "view",
        "type": "function"
    },
    {
        "inputs": [],
        "name": "DEFAULT_ROUND_DURATION",
        "outputs": [
            {
                "internalType": "uint256",
                "name": "",
                "type": "uint256"
            }
        ],
        "stateMutability": "view",
        "type": "function"
    },
    {
        "inputs": [],
        "name": "DIAMOND_NUGGET_PROBABILITY",
        "outputs": [
            {
                "internalType": "uint256",
                "name": "",
                "type": "uint256"
            }
        ],
        "stateMutability": "view",
        "type": "function"
    },
    {
        "inputs": [],
        "name": "EMERALD_VEIN_PROBABILITY",
        "outputs": [
            {
                "internalType": "uint256",
                "name": "",
                "type": "uint256"
            }
        ],
        "stateMutability": "view",
        "type": "function"
    },
    {
        "inputs": [],
        "name": "GOLD_NUGGET_PROBABILITY",
        "outputs": [
            {
                "internalType": "uint256",
                "name": "",
                "type": "uint256"
            }
        ],
        "stateMutability": "view",
        "type": "function"
    },
    {
        "inputs": [],
        "name": "MAX_DEPLOYMENT_PER_SQUARE",
        "outputs": [
            {
                "internalType": "uint256",
                "name": "",
                "type": "uint256"
            }
        ],
        "stateMutability": "view",
        "type": "function"
    },
    {
        "inputs": [],
        "name": "MINING_DURATION",
        "outputs": [
            {
                "internalType": "uint256",
                "name": "",
                "type": "uint256"
            }
        ],
        "stateMutability": "view",
        "type": "function"
    },
    {
        "inputs": [],
        "name": "MIN_DEPLOYMENT",
        "outputs": [
            {
                "internalType": "uint256",
                "name": "",
                "type": "uint256"
            }
        ],
        "stateMutability": "view",
        "type": "function"
    },
    {
        "inputs": [],
        "name": "MOTHERLODE_PROBABILITY",
        "outputs": [
            {
                "internalType": "uint256",
                "name": "",
                "type": "uint256"
            }
        ],
        "stateMutability": "view",
        "type": "function"
    },
    {
        "inputs": [],
        "name": "NUM_MOTHERLODE_TIERS",
        "outputs": [
            {
                "internalType": "uint256",
                "name": "",
                "type": "uint256"
            }
        ],
        "stateMutability": "view",
        "type": "function"
    },
    {
        "inputs": [],
        "name": "NUM_SQUARES",
        "outputs": [
            {
                "internalType": "uint256",
                "name": "",
                "type": "uint256"
            }
        ],
        "stateMutability": "view",
        "type": "function"
    },
    {
        "inputs": [],
        "name": "PARTNER_COMMISSION_BPS",
        "outputs": [
            {
                "internalType": "uint256",
                "name": "",
                "type": "uint256"
            }
        ],
        "stateMutability": "view",
        "type": "function"
    },
    {
        "inputs": [],
        "name": "PLATINUM_NUGGET_PROBABILITY",
        "outputs": [
            {
                "internalType": "uint256",
                "name": "",
                "type": "uint256"
            }
        ],
        "stateMutability": "view",
        "type": "function"
    },
    {
        "inputs": [],
        "name": "REDUCED_ADMIN_FEE_BPS",
        "outputs": [
            {
                "internalType": "uint256",
                "name": "",
                "type": "uint256"
            }
        ],
        "stateMutability": "view",
        "type": "function"
    },
    {
        "inputs": [],
        "name": "RUBY_VEIN_PROBABILITY",
        "outputs": [
            {
                "internalType": "uint256",
                "name": "",
                "type": "uint256"
            }
        ],
        "stateMutability": "view",
        "type": "function"
    },
    {
        "inputs": [],
        "name": "SAPPHIRE_VEIN_PROBABILITY",
        "outputs": [
            {
                "internalType": "uint256",
                "name": "",
                "type": "uint256"
            }
        ],
        "stateMutability": "view",
        "type": "function"
    },
    {
        "inputs": [],
        "name": "SILVER_NUGGET_PROBABILITY",
        "outputs": [
            {
                "internalType": "uint256",
                "name": "",
                "type": "uint256"
            }
        ],
        "stateMutability": "view",
        "type": "function"
    },
    {
        "inputs": [],
        "name": "TOTAL_BTB_REWARDS",
        "outputs": [
            {
                "internalType": "uint256",
                "name": "",
                "type": "uint256"
            }
        ],
        "stateMutability": "view",
        "type": "function"
    },
    {
        "inputs": [],
        "name": "USER_CASHBACK_BPS",
        "outputs": [
            {
                "internalType": "uint256",
                "name": "",
                "type": "uint256"
            }
        ],
        "stateMutability": "view",
        "type": "function"
    },
    {
        "inputs": [
            {
                "internalType": "address[]",
                "name": "users",
                "type": "address[]"
            },
            {
                "internalType": "uint8[][]",
                "name": "squaresArray",
                "type": "uint8[][]"
            },
            {
                "internalType": "uint256[]",
                "name": "amounts",
                "type": "uint256[]"
            },
            {
                "internalType": "address[]",
                "name": "partnersArray",
                "type": "address[]"
            }
        ],
        "name": "batchDeploy",
        "outputs": [],
        "stateMutability": "payable",
        "type": "function"
    },
    {
        "inputs": [],
        "name": "bondingCurveAddress",
        "outputs": [
            {
                "internalType": "address",
                "name": "",
                "type": "address"
            }
        ],
        "stateMutability": "view",
        "type": "function"
    },
    {
        "inputs": [],
        "name": "bronzeNuggetPot",
        "outputs": [
            {
                "internalType": "uint256",
                "name": "",
                "type": "uint256"
            }
        ],
        "stateMutability": "view",
        "type": "function"
    },
    {
        "inputs": [],
        "name": "btbToken",
        "outputs": [
            {
                "internalType": "contract IERC20",
                "name": "",
                "type": "address"
            }
        ],
        "stateMutability": "view",
        "type": "function"
    },
    {
        "inputs": [
            {
                "internalType": "bytes",
                "name": "",
                "type": "bytes"
            }
        ],
        "name": "checkUpkeep",
        "outputs": [
            {
                "internalType": "bool",
                "name": "upkeepNeeded",
                "type": "bool"
            },
            {
                "internalType": "bytes",
                "name": "performData",
                "type": "bytes"
            }
        ],
        "stateMutability": "view",
        "type": "function"
    },
    {
        "inputs": [
            {
                "internalType": "uint256",
                "name": "roundId",
                "type": "uint256"
            }
        ],
        "name": "checkpoint",
        "outputs": [],
        "stateMutability": "nonpayable",
        "type": "function"
    },
    {
        "inputs": [],
        "name": "claimAll",
        "outputs": [],
        "stateMutability": "nonpayable",
        "type": "function"
    },
    {
        "inputs": [],
        "name": "claimBTB",
        "outputs": [],
        "stateMutability": "nonpayable",
        "type": "function"
    },
    {
        "inputs": [],
        "name": "claimETH",
        "outputs": [],
        "stateMutability": "nonpayable",
        "type": "function"
    },
    {
        "inputs": [],
        "name": "clearPendingVRFRequest",
        "outputs": [],
        "stateMutability": "nonpayable",
        "type": "function"
    },
    {
        "inputs": [],
        "name": "crystalCachePot",
        "outputs": [
            {
                "internalType": "uint256",
                "name": "",
                "type": "uint256"
            }
        ],
        "stateMutability": "view",
        "type": "function"
    },
    {
        "inputs": [],
        "name": "currentRoundId",
        "outputs": [
            {
                "internalType": "uint256",
                "name": "",
                "type": "uint256"
            }
        ],
        "stateMutability": "view",
        "type": "function"
    },
    {
        "inputs": [
            {
                "internalType": "uint8[]",
                "name": "squares",
                "type": "uint8[]"
            },
            {
                "internalType": "uint256",
                "name": "amountPerSquare",
                "type": "uint256"
            },
            {
                "internalType": "address",
                "name": "partner",
                "type": "address"
            }
        ],
        "name": "deploy",
        "outputs": [],
        "stateMutability": "payable",
        "type": "function"
    },
    {
        "inputs": [],
        "name": "diamondNuggetPot",
        "outputs": [
            {
                "internalType": "uint256",
                "name": "",
                "type": "uint256"
            }
        ],
        "stateMutability": "view",
        "type": "function"
    },
    {
        "inputs": [],
        "name": "emeraldVeinPot",
        "outputs": [
            {
                "internalType": "uint256",
                "name": "",
                "type": "uint256"
            }
        ],
        "stateMutability": "view",
        "type": "function"
    },
    {
        "inputs": [
            {
                "internalType": "address",
                "name": "recipient",
                "type": "address"
            }
        ],
        "name": "emergencyWithdrawBTB",
        "outputs": [],
        "stateMutability": "nonpayable",
        "type": "function"
    },
    {
        "inputs": [
            {
                "internalType": "address",
                "name": "recipient",
                "type": "address"
            },
            {
                "internalType": "uint256",
                "name": "amount",
                "type": "uint256"
            }
        ],
        "name": "emergencyWithdrawETH",
        "outputs": [],
        "stateMutability": "nonpayable",
        "type": "function"
    },
    {
        "inputs": [],
        "name": "endTime",
        "outputs": [
            {
                "internalType": "uint256",
                "name": "",
                "type": "uint256"
            }
        ],
        "stateMutability": "view",
        "type": "function"
    },
    {
        "inputs": [
            {
                "internalType": "uint256",
                "name": "roundId",
                "type": "uint256"
            },
            {
                "internalType": "address",
                "name": "miner",
                "type": "address"
            },
            {
                "internalType": "uint8",
                "name": "square",
                "type": "uint8"
            }
        ],
        "name": "estimateRewards",
        "outputs": [
            {
                "internalType": "uint256",
                "name": "estimatedETH",
                "type": "uint256"
            },
            {
                "internalType": "uint256",
                "name": "estimatedBTB",
                "type": "uint256"
            }
        ],
        "stateMutability": "view",
        "type": "function"
    },
    {
        "inputs": [],
        "name": "finalizeRound",
        "outputs": [],
        "stateMutability": "nonpayable",
        "type": "function"
    },
    {
        "inputs": [],
        "name": "getAllMotherloadePots",
        "outputs": [
            {
                "internalType": "uint256[10]",
                "name": "pots",
                "type": "uint256[10]"
            }
        ],
        "stateMutability": "view",
        "type": "function"
    },
    {
        "inputs": [],
        "name": "getAllPartners",
        "outputs": [
            {
                "internalType": "address[]",
                "name": "",
                "type": "address[]"
            }
        ],
        "stateMutability": "view",
        "type": "function"
    },
    {
        "inputs": [],
        "name": "getCurrentRound",
        "outputs": [
            {
                "components": [
                    {
                        "internalType": "uint256",
                        "name": "id",
                        "type": "uint256"
                    },
                    {
                        "internalType": "uint256",
                        "name": "startTime",
                        "type": "uint256"
                    },
                    {
                        "internalType": "uint256",
                        "name": "endTime",
                        "type": "uint256"
                    },
                    {
                        "internalType": "uint256[25]",
                        "name": "deployed",
                        "type": "uint256[25]"
                    },
                    {
                        "internalType": "uint256[25]",
                        "name": "minerCount",
                        "type": "uint256[25]"
                    },
                    {
                        "internalType": "uint256",
                        "name": "totalDeployed",
                        "type": "uint256"
                    },
                    {
                        "internalType": "bytes32",
                        "name": "entropyHash",
                        "type": "bytes32"
                    },
                    {
                        "internalType": "uint256",
                        "name": "totalWinnings",
                        "type": "uint256"
                    },
                    {
                        "internalType": "uint256",
                        "name": "btbReward",
                        "type": "uint256"
                    },
                    {
                        "internalType": "uint256",
                        "name": "totalMotherlodeReward",
                        "type": "uint256"
                    },
                    {
                        "internalType": "uint8",
                        "name": "winningSquare",
                        "type": "uint8"
                    },
                    {
                        "internalType": "uint16",
                        "name": "motherlodeTiersHit",
                        "type": "uint16"
                    },
                    {
                        "internalType": "bool",
                        "name": "finalized",
                        "type": "bool"
                    },
                    {
                        "internalType": "bool",
                        "name": "isCheckpointable",
                        "type": "bool"
                    },
                    {
                        "internalType": "bool",
                        "name": "isJackpotRound",
                        "type": "bool"
                    },
                    {
                        "internalType": "bool",
                        "name": "timerStarted",
                        "type": "bool"
                    },
                    {
                        "internalType": "bool",
                        "name": "finalizationRequested",
                        "type": "bool"
                    }
                ],
                "internalType": "struct BTBMining.Round",
                "name": "",
                "type": "tuple"
            }
        ],
        "stateMutability": "view",
        "type": "function"
    },
    {
        "inputs": [],
        "name": "getCurrentRoundTimeRemaining",
        "outputs": [
            {
                "internalType": "uint256",
                "name": "",
                "type": "uint256"
            }
        ],
        "stateMutability": "view",
        "type": "function"
    },
    {
        "inputs": [
            {
                "internalType": "address",
                "name": "miner",
                "type": "address"
            }
        ],
        "name": "getMinerBTBBreakdown",
        "outputs": [
            {
                "internalType": "uint256",
                "name": "unclaimedBTB",
                "type": "uint256"
            },
            {
                "internalType": "uint256",
                "name": "refinedBTB",
                "type": "uint256"
            },
            {
                "internalType": "uint256",
                "name": "pendingRefined",
                "type": "uint256"
            },
            {
                "internalType": "uint256",
                "name": "totalClaimable",
                "type": "uint256"
            }
        ],
        "stateMutability": "view",
        "type": "function"
    },
    {
        "inputs": [
            {
                "internalType": "uint256",
                "name": "roundId",
                "type": "uint256"
            },
            {
                "internalType": "address",
                "name": "miner",
                "type": "address"
            }
        ],
        "name": "getMinerRoundData",
        "outputs": [
            {
                "components": [
                    {
                        "internalType": "uint256[25]",
                        "name": "deployed",
                        "type": "uint256[25]"
                    },
                    {
                        "internalType": "bool",
                        "name": "hasCheckpointed",
                        "type": "bool"
                    },
                    {
                        "internalType": "uint256",
                        "name": "rewardsETH",
                        "type": "uint256"
                    },
                    {
                        "internalType": "uint256",
                        "name": "rewardsBTB",
                        "type": "uint256"
                    },
                    {
                        "internalType": "uint256",
                        "name": "refinedBTB",
                        "type": "uint256"
                    },
                    {
                        "internalType": "uint256",
                        "name": "lastRewardsFactor",
                        "type": "uint256"
                    }
                ],
                "internalType": "struct BTBMining.MinerRoundData",
                "name": "",
                "type": "tuple"
            }
        ],
        "stateMutability": "view",
        "type": "function"
    },
    {
        "inputs": [
            {
                "internalType": "address",
                "name": "",
                "type": "address"
            }
        ],
        "name": "getMinerStats",
        "outputs": [
            {
                "internalType": "uint256",
                "name": "ethEarned",
                "type": "uint256"
            },
            {
                "internalType": "uint256",
                "name": "btbEarned",
                "type": "uint256"
            },
            {
                "internalType": "uint256",
                "name": "roundsPlayed",
                "type": "uint256"
            },
            {
                "internalType": "uint256",
                "name": "roundsWon",
                "type": "uint256"
            },
            {
                "internalType": "uint256",
                "name": "winRate",
                "type": "uint256"
            }
        ],
        "stateMutability": "pure",
        "type": "function"
    },
    {
        "inputs": [
            {
                "internalType": "uint8",
                "name": "tier",
                "type": "uint8"
            }
        ],
        "name": "getMotherloadeTierInfo",
        "outputs": [
            {
                "internalType": "string",
                "name": "name",
                "type": "string"
            },
            {
                "internalType": "uint256",
                "name": "currentPot",
                "type": "uint256"
            },
            {
                "internalType": "uint256",
                "name": "perRoundIncrease",
                "type": "uint256"
            },
            {
                "internalType": "uint256",
                "name": "probability",
                "type": "uint256"
            }
        ],
        "stateMutability": "view",
        "type": "function"
    },
    {
        "inputs": [
            {
                "internalType": "address",
                "name": "partner",
                "type": "address"
            }
        ],
        "name": "getPartnerInfo",
        "outputs": [
            {
                "internalType": "bool",
                "name": "isWhitelisted",
                "type": "bool"
            },
            {
                "internalType": "string",
                "name": "name",
                "type": "string"
            },
            {
                "internalType": "uint256",
                "name": "accumulatedFees",
                "type": "uint256"
            },
            {
                "internalType": "uint256",
                "name": "totalReferrals",
                "type": "uint256"
            },
            {
                "internalType": "uint256",
                "name": "totalVolumeReferred",
                "type": "uint256"
            }
        ],
        "stateMutability": "view",
        "type": "function"
    },
    {
        "inputs": [
            {
                "internalType": "uint256",
                "name": "roundId",
                "type": "uint256"
            }
        ],
        "name": "getRound",
        "outputs": [
            {
                "components": [
                    {
                        "internalType": "uint256",
                        "name": "id",
                        "type": "uint256"
                    },
                    {
                        "internalType": "uint256",
                        "name": "startTime",
                        "type": "uint256"
                    },
                    {
                        "internalType": "uint256",
                        "name": "endTime",
                        "type": "uint256"
                    },
                    {
                        "internalType": "uint256[25]",
                        "name": "deployed",
                        "type": "uint256[25]"
                    },
                    {
                        "internalType": "uint256[25]",
                        "name": "minerCount",
                        "type": "uint256[25]"
                    },
                    {
                        "internalType": "uint256",
                        "name": "totalDeployed",
                        "type": "uint256"
                    },
                    {
                        "internalType": "bytes32",
                        "name": "entropyHash",
                        "type": "bytes32"
                    },
                    {
                        "internalType": "uint256",
                        "name": "totalWinnings",
                        "type": "uint256"
                    },
                    {
                        "internalType": "uint256",
                        "name": "btbReward",
                        "type": "uint256"
                    },
                    {
                        "internalType": "uint256",
                        "name": "totalMotherlodeReward",
                        "type": "uint256"
                    },
                    {
                        "internalType": "uint8",
                        "name": "winningSquare",
                        "type": "uint8"
                    },
                    {
                        "internalType": "uint16",
                        "name": "motherlodeTiersHit",
                        "type": "uint16"
                    },
                    {
                        "internalType": "bool",
                        "name": "finalized",
                        "type": "bool"
                    },
                    {
                        "internalType": "bool",
                        "name": "isCheckpointable",
                        "type": "bool"
                    },
                    {
                        "internalType": "bool",
                        "name": "isJackpotRound",
                        "type": "bool"
                    },
                    {
                        "internalType": "bool",
                        "name": "timerStarted",
                        "type": "bool"
                    },
                    {
                        "internalType": "bool",
                        "name": "finalizationRequested",
                        "type": "bool"
                    }
                ],
                "internalType": "struct BTBMining.Round",
                "name": "",
                "type": "tuple"
            }
        ],
        "stateMutability": "view",
        "type": "function"
    },
    {
        "inputs": [
            {
                "internalType": "uint256",
                "name": "roundId",
                "type": "uint256"
            }
        ],
        "name": "getRoundMotherlodeHits",
        "outputs": [
            {
                "internalType": "bool[10]",
                "name": "tiersHit",
                "type": "bool[10]"
            }
        ],
        "stateMutability": "view",
        "type": "function"
    },
    {
        "inputs": [
            {
                "internalType": "uint256",
                "name": "roundId",
                "type": "uint256"
            },
            {
                "internalType": "uint8",
                "name": "square",
                "type": "uint8"
            }
        ],
        "name": "getSquareDeployment",
        "outputs": [
            {
                "internalType": "uint256",
                "name": "totalDeployed",
                "type": "uint256"
            },
            {
                "internalType": "uint256",
                "name": "minerCount",
                "type": "uint256"
            }
        ],
        "stateMutability": "view",
        "type": "function"
    },
    {
        "inputs": [],
        "name": "getTokenDistribution",
        "outputs": [
            {
                "internalType": "uint256",
                "name": "treasuryBalance",
                "type": "uint256"
            },
            {
                "internalType": "uint256",
                "name": "contractBalance",
                "type": "uint256"
            },
            {
                "internalType": "uint256",
                "name": "totalDistributed",
                "type": "uint256"
            }
        ],
        "stateMutability": "view",
        "type": "function"
    },
    {
        "inputs": [
            {
                "internalType": "address",
                "name": "miner",
                "type": "address"
            }
        ],
        "name": "getTotalClaimableBalance",
        "outputs": [
            {
                "internalType": "uint256",
                "name": "totalETH",
                "type": "uint256"
            },
            {
                "internalType": "uint256",
                "name": "totalBTB",
                "type": "uint256"
            }
        ],
        "stateMutability": "view",
        "type": "function"
    },
    {
        "inputs": [],
        "name": "getTreasuryInfo",
        "outputs": [
            {
                "internalType": "uint256",
                "name": "totalUnclaimed",
                "type": "uint256"
            },
            {
                "internalType": "uint256",
                "name": "totalRefined",
                "type": "uint256"
            },
            {
                "internalType": "uint256",
                "name": "currentRewardsFactor",
                "type": "uint256"
            }
        ],
        "stateMutability": "view",
        "type": "function"
    },
    {
        "inputs": [
            {
                "internalType": "uint256",
                "name": "roundId",
                "type": "uint256"
            }
        ],
        "name": "getWinningSquare",
        "outputs": [
            {
                "internalType": "uint8",
                "name": "",
                "type": "uint8"
            }
        ],
        "stateMutability": "view",
        "type": "function"
    },
    {
        "inputs": [],
        "name": "goldNuggetPot",
        "outputs": [
            {
                "internalType": "uint256",
                "name": "",
                "type": "uint256"
            }
        ],
        "stateMutability": "view",
        "type": "function"
    },
    {
        "inputs": [
            {
                "internalType": "address",
                "name": "_owner",
                "type": "address"
            },
            {
                "internalType": "address",
                "name": "_btbToken",
                "type": "address"
            },
            {
                "internalType": "address",
                "name": "_vrfCoordinator",
                "type": "address"
            }
        ],
        "name": "initialize",
        "outputs": [],
        "stateMutability": "nonpayable",
        "type": "function"
    },
    {
        "inputs": [
            {
                "internalType": "uint256",
                "name": "",
                "type": "uint256"
            },
            {
                "internalType": "address",
                "name": "",
                "type": "address"
            }
        ],
        "name": "minerData",
        "outputs": [
            {
                "internalType": "bool",
                "name": "hasCheckpointed",
                "type": "bool"
            },
            {
                "internalType": "uint256",
                "name": "rewardsETH",
                "type": "uint256"
            },
            {
                "internalType": "uint256",
                "name": "rewardsBTB",
                "type": "uint256"
            },
            {
                "internalType": "uint256",
                "name": "refinedBTB",
                "type": "uint256"
            },
            {
                "internalType": "uint256",
                "name": "lastRewardsFactor",
                "type": "uint256"
            }
        ],
        "stateMutability": "view",
        "type": "function"
    },
    {
        "inputs": [
            {
                "internalType": "address",
                "name": "",
                "type": "address"
            },
            {
                "internalType": "uint256",
                "name": "",
                "type": "uint256"
            }
        ],
        "name": "minerParticipatedRounds",
        "outputs": [
            {
                "internalType": "uint256",
                "name": "",
                "type": "uint256"
            }
        ],
        "stateMutability": "view",
        "type": "function"
    },
    {
        "inputs": [
            {
                "internalType": "address",
                "name": "",
                "type": "address"
            }
        ],
        "name": "minerStats",
        "outputs": [
            {
                "internalType": "uint256",
                "name": "unclaimedETH",
                "type": "uint256"
            },
            {
                "internalType": "uint256",
                "name": "unclaimedBTB",
                "type": "uint256"
            },
            {
                "internalType": "uint256",
                "name": "refinedBTB",
                "type": "uint256"
            },
            {
                "internalType": "uint256",
                "name": "lastRewardsFactor",
                "type": "uint256"
            }
        ],
        "stateMutability": "view",
        "type": "function"
    },
    {
        "inputs": [],
        "name": "motherloadePot",
        "outputs": [
            {
                "internalType": "uint256",
                "name": "",
                "type": "uint256"
            }
        ],
        "stateMutability": "view",
        "type": "function"
    },
    {
        "inputs": [],
        "name": "owner",
        "outputs": [
            {
                "internalType": "address",
                "name": "",
                "type": "address"
            }
        ],
        "stateMutability": "view",
        "type": "function"
    },
    {
        "inputs": [
            {
                "internalType": "uint256",
                "name": "",
                "type": "uint256"
            }
        ],
        "name": "partnerList",
        "outputs": [
            {
                "internalType": "address",
                "name": "",
                "type": "address"
            }
        ],
        "stateMutability": "view",
        "type": "function"
    },
    {
        "inputs": [
            {
                "internalType": "address",
                "name": "",
                "type": "address"
            }
        ],
        "name": "partners",
        "outputs": [
            {
                "internalType": "bool",
                "name": "isWhitelisted",
                "type": "bool"
            },
            {
                "internalType": "string",
                "name": "name",
                "type": "string"
            },
            {
                "internalType": "uint256",
                "name": "accumulatedFees",
                "type": "uint256"
            },
            {
                "internalType": "uint256",
                "name": "totalReferrals",
                "type": "uint256"
            },
            {
                "internalType": "uint256",
                "name": "totalVolumeReferred",
                "type": "uint256"
            }
        ],
        "stateMutability": "view",
        "type": "function"
    },
    {
        "inputs": [],
        "name": "pendingVRFRequest",
        "outputs": [
            {
                "internalType": "uint256",
                "name": "",
                "type": "uint256"
            }
        ],
        "stateMutability": "view",
        "type": "function"
    },
    {
        "inputs": [
            {
                "internalType": "bytes",
                "name": "",
                "type": "bytes"
            }
        ],
        "name": "performUpkeep",
        "outputs": [],
        "stateMutability": "nonpayable",
        "type": "function"
    },
    {
        "inputs": [],
        "name": "platinumNuggetPot",
        "outputs": [
            {
                "internalType": "uint256",
                "name": "",
                "type": "uint256"
            }
        ],
        "stateMutability": "view",
        "type": "function"
    },
    {
        "inputs": [
            {
                "internalType": "uint256",
                "name": "roundId",
                "type": "uint256"
            }
        ],
        "name": "pruneRoundData",
        "outputs": [],
        "stateMutability": "nonpayable",
        "type": "function"
    },
    {
        "inputs": [
            {
                "internalType": "uint256",
                "name": "requestId",
                "type": "uint256"
            },
            {
                "internalType": "uint256[]",
                "name": "randomWords",
                "type": "uint256[]"
            }
        ],
        "name": "rawFulfillRandomWords",
        "outputs": [],
        "stateMutability": "nonpayable",
        "type": "function"
    },
    {
        "inputs": [
            {
                "internalType": "address",
                "name": "partner",
                "type": "address"
            }
        ],
        "name": "removePartner",
        "outputs": [],
        "stateMutability": "nonpayable",
        "type": "function"
    },
    {
        "inputs": [],
        "name": "renounceOwnership",
        "outputs": [],
        "stateMutability": "nonpayable",
        "type": "function"
    },
    {
        "inputs": [],
        "name": "rewardsFactor",
        "outputs": [
            {
                "internalType": "uint256",
                "name": "",
                "type": "uint256"
            }
        ],
        "stateMutability": "view",
        "type": "function"
    },
    {
        "inputs": [],
        "name": "roundDuration",
        "outputs": [
            {
                "internalType": "uint256",
                "name": "",
                "type": "uint256"
            }
        ],
        "stateMutability": "view",
        "type": "function"
    },
    {
        "inputs": [
            {
                "internalType": "uint256",
                "name": "",
                "type": "uint256"
            }
        ],
        "name": "rounds",
        "outputs": [
            {
                "internalType": "uint256",
                "name": "id",
                "type": "uint256"
            },
            {
                "internalType": "uint256",
                "name": "startTime",
                "type": "uint256"
            },
            {
                "internalType": "uint256",
                "name": "endTime",
                "type": "uint256"
            },
            {
                "internalType": "uint256",
                "name": "totalDeployed",
                "type": "uint256"
            },
            {
                "internalType": "bytes32",
                "name": "entropyHash",
                "type": "bytes32"
            },
            {
                "internalType": "uint256",
                "name": "totalWinnings",
                "type": "uint256"
            },
            {
                "internalType": "uint256",
                "name": "btbReward",
                "type": "uint256"
            },
            {
                "internalType": "uint256",
                "name": "totalMotherlodeReward",
                "type": "uint256"
            },
            {
                "internalType": "uint8",
                "name": "winningSquare",
                "type": "uint8"
            },
            {
                "internalType": "uint16",
                "name": "motherlodeTiersHit",
                "type": "uint16"
            },
            {
                "internalType": "bool",
                "name": "finalized",
                "type": "bool"
            },
            {
                "internalType": "bool",
                "name": "isCheckpointable",
                "type": "bool"
            },
            {
                "internalType": "bool",
                "name": "isJackpotRound",
                "type": "bool"
            },
            {
                "internalType": "bool",
                "name": "timerStarted",
                "type": "bool"
            },
            {
                "internalType": "bool",
                "name": "finalizationRequested",
                "type": "bool"
            }
        ],
        "stateMutability": "view",
        "type": "function"
    },
    {
        "inputs": [],
        "name": "rubyVeinPot",
        "outputs": [
            {
                "internalType": "uint256",
                "name": "",
                "type": "uint256"
            }
        ],
        "stateMutability": "view",
        "type": "function"
    },
    {
        "inputs": [],
        "name": "sapphireVeinPot",
        "outputs": [
            {
                "internalType": "uint256",
                "name": "",
                "type": "uint256"
            }
        ],
        "stateMutability": "view",
        "type": "function"
    },
    {
        "inputs": [
            {
                "internalType": "address",
                "name": "_bondingCurveAddress",
                "type": "address"
            }
        ],
        "name": "setBondingCurveAddress",
        "outputs": [],
        "stateMutability": "nonpayable",
        "type": "function"
    },
    {
        "inputs": [
            {
                "internalType": "uint256",
                "name": "_newDuration",
                "type": "uint256"
            }
        ],
        "name": "setRoundDuration",
        "outputs": [],
        "stateMutability": "nonpayable",
        "type": "function"
    },
    {
        "inputs": [
            {
                "internalType": "address",
                "name": "_treasuryAddress",
                "type": "address"
            }
        ],
        "name": "setTreasuryAddress",
        "outputs": [],
        "stateMutability": "nonpayable",
        "type": "function"
    },
    {
        "inputs": [
            {
                "internalType": "uint256",
                "name": "_subscriptionId",
                "type": "uint256"
            },
            {
                "internalType": "bytes32",
                "name": "_keyHash",
                "type": "bytes32"
            },
            {
                "internalType": "uint32",
                "name": "_callbackGasLimit",
                "type": "uint32"
            },
            {
                "internalType": "uint16",
                "name": "_requestConfirmations",
                "type": "uint16"
            }
        ],
        "name": "setVRFConfig",
        "outputs": [],
        "stateMutability": "nonpayable",
        "type": "function"
    },
    {
        "inputs": [],
        "name": "silverNuggetPot",
        "outputs": [
            {
                "internalType": "uint256",
                "name": "",
                "type": "uint256"
            }
        ],
        "stateMutability": "view",
        "type": "function"
    },
    {
        "inputs": [],
        "name": "startTime",
        "outputs": [
            {
                "internalType": "uint256",
                "name": "",
                "type": "uint256"
            }
        ],
        "stateMutability": "view",
        "type": "function"
    },
    {
        "inputs": [],
        "name": "totalRefinedBTB",
        "outputs": [
            {
                "internalType": "uint256",
                "name": "",
                "type": "uint256"
            }
        ],
        "stateMutability": "view",
        "type": "function"
    },
    {
        "inputs": [],
        "name": "totalUnclaimedBTB",
        "outputs": [
            {
                "internalType": "uint256",
                "name": "",
                "type": "uint256"
            }
        ],
        "stateMutability": "view",
        "type": "function"
    },
    {
        "inputs": [
            {
                "internalType": "address",
                "name": "newOwner",
                "type": "address"
            }
        ],
        "name": "transferOwnership",
        "outputs": [],
        "stateMutability": "nonpayable",
        "type": "function"
    },
    {
        "inputs": [],
        "name": "treasuryAddress",
        "outputs": [
            {
                "internalType": "address",
                "name": "",
                "type": "address"
            }
        ],
        "stateMutability": "view",
        "type": "function"
    },
    {
        "inputs": [],
        "name": "vrfCallbackGasLimit",
        "outputs": [
            {
                "internalType": "uint32",
                "name": "",
                "type": "uint32"
            }
        ],
        "stateMutability": "view",
        "type": "function"
    },
    {
        "inputs": [],
        "name": "vrfCoordinator",
        "outputs": [
            {
                "internalType": "contract IVRFCoordinatorV2Plus",
                "name": "",
                "type": "address"
            }
        ],
        "stateMutability": "view",
        "type": "function"
    },
    {
        "inputs": [],
        "name": "vrfKeyHash",
        "outputs": [
            {
                "internalType": "bytes32",
                "name": "",
                "type": "bytes32"
            }
        ],
        "stateMutability": "view",
        "type": "function"
    },
    {
        "inputs": [],
        "name": "vrfRequestConfirmations",
        "outputs": [
            {
                "internalType": "uint16",
                "name": "",
                "type": "uint16"
            }
        ],
        "stateMutability": "view",
        "type": "function"
    },
    {
        "inputs": [
            {
                "internalType": "uint256",
                "name": "",
                "type": "uint256"
            }
        ],
        "name": "vrfRequestToRound",
        "outputs": [
            {
                "internalType": "uint256",
                "name": "",
                "type": "uint256"
            }
        ],
        "stateMutability": "view",
        "type": "function"
    },
    {
        "inputs": [],
        "name": "vrfSubscriptionId",
        "outputs": [
            {
                "internalType": "uint256",
                "name": "",
                "type": "uint256"
            }
        ],
        "stateMutability": "view",
        "type": "function"
    },
    {
        "inputs": [
            {
                "internalType": "address",
                "name": "partner",
                "type": "address"
            },
            {
                "internalType": "string",
                "name": "name",
                "type": "string"
            }
        ],
        "name": "whitelistPartner",
        "outputs": [],
        "stateMutability": "nonpayable",
        "type": "function"
    },
    {
        "inputs": [],
        "name": "withdrawFromTreasury",
        "outputs": [],
        "stateMutability": "nonpayable",
        "type": "function"
    },
    {
        "inputs": [
            {
                "internalType": "address",
                "name": "recipient",
                "type": "address"
            }
        ],
        "name": "withdrawPartnerFees",
        "outputs": [],
        "stateMutability": "nonpayable",
        "type": "function"
    },
    {
        "stateMutability": "payable",
        "type": "receive"
    }
]